counter_robots/__init__.py
counter_robots/data/machine.txt
counter_robots/data/robot.txt
counter_robots-2025.11.dist-info/licenses/AUTHORS.rst
counter_robots-2025.11.dist-info/licenses/LICENSE
counter_robots-2025.11.dist-info/METADATA
counter_robots-2025.11.dist-info/WHEEL
counter_robots-2025.11.dist-info/top_level.txt
counter_robots-2025.11.dist-info/RECORD
