Metadata-Version: 2.4
Name: counter-robots
Version: 2025.11
Summary: Library for COUNTER-compliant detection of machines and robots.
Home-page: https://github.com/inveniosoftware/counter-robots
Author: Invenio Software
Author-email: info@inveniosoftware.org
License: MIT
Keywords: COUNTER,user-agent,robot detection
Platform: any
Classifier: Development Status :: 5 - Production/Stable
Requires-Python: >=3.9
License-File: LICENSE
License-File: AUTHORS.rst
Provides-Extra: tests
Requires-Dist: pytest-black>=0.6.0; extra == "tests"
Requires-Dist: pytest-invenio<4.0.0,>=3.0.0; extra == "tests"
Requires-Dist: Sphinx>=4.5.0; extra == "tests"
Provides-Extra: docs
Dynamic: license-file
